cxr_sdk/__init__.py
cxr_sdk/cli.py
cxr_sdk/client.py
cxr_sdk-0.1.0.dist-info/METADATA
cxr_sdk-0.1.0.dist-info/WHEEL
cxr_sdk-0.1.0.dist-info/entry_points.txt
cxr_sdk-0.1.0.dist-info/top_level.txt
cxr_sdk-0.1.0.dist-info/RECORD
