Metadata-Version: 2.4
Name: cxr-sdk
Version: 0.1.0
Summary: Official Python SDK for the CXR SaaS API - Claim Reasoning Engine
Author-email: CXR Platform Team <platform@cxrlabs.org>
License: Proprietary
Keywords: cxr,claims,healthcare,medicare,denials,sdk
Classifier: Development Status :: 4 - Beta
Classifier: Intended Audience :: Developers
Classifier: Programming Language :: Python :: 3
Classifier: Programming Language :: Python :: 3.10
Classifier: Programming Language :: Python :: 3.11
Classifier: Programming Language :: Python :: 3.12
Requires-Python: >=3.10
Requires-Dist: httpx>=0.28
Requires-Dist: pydantic>=2.5
Provides-Extra: dev
Requires-Dist: pytest>=7.4; extra == "dev"
Requires-Dist: pytest-asyncio>=0.20; extra == "dev"
Requires-Dist: respx>=0.22; extra == "dev"
